logmine-0.4.1.data/scripts/logmine
logmine_pkg/__init__.py
logmine_pkg/cli_input.py
logmine_pkg/cluster_merge.py
logmine_pkg/cluster_merge_test.py
logmine_pkg/clusterer.py
logmine_pkg/clusterer_test.py
logmine_pkg/debug.py
logmine_pkg/file_segment_reader.py
logmine_pkg/file_segment_reader_test.py
logmine_pkg/legacy_import_test.py
logmine_pkg/line_scorer.py
logmine_pkg/line_scorer_test.py
logmine_pkg/log_mine.py
logmine_pkg/map_reduce.py
logmine_pkg/output.py
logmine_pkg/pattern_generator.py
logmine_pkg/pattern_generator_test.py
logmine_pkg/preprocessor.py
logmine_pkg/preprocessor_test.py
logmine_pkg/processor.py
logmine_pkg/run.py
logmine_pkg/segmentator.py
logmine_pkg/segmentator_test.py
logmine_pkg/variable.py
logmine_pkg/vendor/__init__.py
logmine_pkg/vendor/alignment.py
src/__init__.py
src/cli_input.py
src/cluster_merge.py
src/cluster_merge_test.py
src/clusterer.py
src/clusterer_test.py
src/debug.py
src/file_segment_reader.py
src/file_segment_reader_test.py
src/line_scorer.py
src/line_scorer_test.py
src/log_mine.py
src/map_reduce.py
src/output.py
src/pattern_generator.py
src/pattern_generator_test.py
src/preprocessor.py
src/preprocessor_test.py
src/processor.py
src/run.py
src/segmentator.py
src/segmentator_test.py
src/variable.py
src/log_mine/__init__.py
src/vendor/__init__.py
src/vendor/alignment.py
logmine-0.4.1.dist-info/LICENSE
logmine-0.4.1.dist-info/METADATA
logmine-0.4.1.dist-info/WHEEL
logmine-0.4.1.dist-info/top_level.txt
logmine-0.4.1.dist-info/RECORD
