Metadata-Version: 2.1
Name: logmine
Version: 0.4.1
Summary: Log pattern analyzer
Home-page: https://github.com/trungdq88/logmine
Author: Tony Dinh
Author-email: pip@tonydinh.com
License: UNKNOWN
Platform: UNKNOWN
Classifier: Programming Language :: Python :: 3
Classifier: License :: OSI Approved :: MIT License
Classifier: Operating System :: OS Independent
